LICENSE
MANIFEST.in
README.rst
setup.py
example_project/app/__init__.py
example_project/app/gutter.py
gutter/__init__.py
gutter/django/__init__.py
gutter/django/autodiscovery.py
gutter/django/forms.py
gutter/django/helpers.py
gutter/django/nexus_modules.py
gutter/django/registry.py
gutter/django/media/css/gutter.css
gutter/django/media/img/button-bg.jpg
gutter/django/media/img/delete.png
gutter/django/media/img/edit.png
gutter/django/media/js/gutter.js
gutter/django/media/js/string_score.min.js
gutter/django/templates/gutter/index.html
gutter/django/templates/gutter/switch.html
gutter/django/templates/gutter/switch_block.html
gutter/django/templates/gutter/nexus/dashboard.html
gutter/django/templatetags/__init__.py
gutter/django/templatetags/gutter_helpers.py
gutter_django.egg-info/PKG-INFO
gutter_django.egg-info/SOURCES.txt
gutter_django.egg-info/dependency_links.txt
gutter_django.egg-info/namespace_packages.txt
gutter_django.egg-info/not-zip-safe
gutter_django.egg-info/requires.txt
gutter_django.egg-info/top_level.txt