Metadata-Version: 1.1
Name: gutter-django
Version: 0.1.13
Summary: Web UI to administer Gutter switches.
Home-page: http://github.com/disqus/gutter-django
Author: DISQUS
Author-email: opensource@disqus.com
License: Apache License 2.0
Platform: UNKNOWN
Classifier: Framework :: Django
Classifier: Intended Audience :: Developers
Classifier: Intended Audience :: System Administrators
Classifier: Operating System :: OS Independent
Classifier: Topic :: Software Development
